deploymentutils/__init__.py
deploymentutils/core.py
deploymentutils/multi_search_and_replace.py
deploymentutils/release.py
deploymentutils/script.py
deploymentutils/search_and_replace.py
deploymentutils-0.11.1.dist-info/licenses/LICENSE
deploymentutils-0.11.1.dist-info/METADATA
deploymentutils-0.11.1.dist-info/WHEEL
deploymentutils-0.11.1.dist-info/entry_points.txt
deploymentutils-0.11.1.dist-info/top_level.txt
deploymentutils-0.11.1.dist-info/RECORD
