Metadata-Version: 2.4
Name: deploymentutils
Version: 0.11.1
Summary: Small python package to facilitate deployment of some personal projects.
Author: Carsten Knoll
Author-email: carsten.knoll@posteo.de
License: GNU General Public License v3
Keywords: ssh,remote execution
Classifier: Development Status :: 3 - Alpha
Classifier: License :: OSI Approved :: GNU General Public License v3 (GPLv3)
Classifier: Programming Language :: Python :: 3
License-File: LICENSE
Requires-Dist: fabric>=2.5.0
Requires-Dist: ipydex>=0.10.0
Requires-Dist: colorama>=0.4.0
Requires-Dist: jinja2>=0.2.0
Requires-Dist: python-decouple>=3.3
Requires-Dist: tomli>=1.1.0; python_version < "3.11"
Requires-Dist: typing_extensions
Requires-Dist: requests
Requires-Dist: pyyaml
Dynamic: author
Dynamic: author-email
Dynamic: classifier
Dynamic: description
Dynamic: description-content-type
Dynamic: keywords
Dynamic: license
Dynamic: license-file
Dynamic: requires-dist
Dynamic: summary
